analyse_exec_utils/__init__.py
analyse_exec_utils/calculate_time.py
analyse_exec_utils-0.0.3.dist-info/LICENSE
analyse_exec_utils-0.0.3.dist-info/METADATA
analyse_exec_utils-0.0.3.dist-info/WHEEL
analyse_exec_utils-0.0.3.dist-info/top_level.txt
analyse_exec_utils-0.0.3.dist-info/RECORD
